setup.py
Flask_SSDB.egg-info/PKG-INFO
Flask_SSDB.egg-info/SOURCES.txt
Flask_SSDB.egg-info/dependency_links.txt
Flask_SSDB.egg-info/namespace_packages.txt
Flask_SSDB.egg-info/not-zip-safe
Flask_SSDB.egg-info/requires.txt
Flask_SSDB.egg-info/top_level.txt
flaskext/__init__.py
flaskext/ssdb.py