Metadata-Version: 1.1
Name: Flask-SSDB
Version: 0.0.1
Summary: Flask simple ssdb client
Home-page: https://github.com/Microndgt/flask_ssdb/
Author: Kevin Du
Author-email: dgt_x@foxmail.com
License: BSD
Platform: any
Classifier: Environment :: Web Environment
Classifier: Intended Audience :: Developers
Classifier: License :: OSI Approved :: BSD License
Classifier: Operating System :: OS Independent
Classifier: Programming Language :: Python
Classifier: Topic :: Internet :: WWW/HTTP :: Dynamic Content
Classifier: Topic :: Software Development :: Libraries :: Python Modules
